{
  "model_name": "Three-Level Temporal Hierarchy Agent",
  "version": "1.0",
  "annotation": "A three-level hierarchical Active Inference agent with distinct temporal scales:\n\n- Level 0 (fast, 100ms): Sensorimotor control \u2014 immediate reflexive responses\n- Level 1 (medium, 1s): Tactical planning \u2014 goal-directed behavior sequences\n- Level 2 (slow, 10s): Strategic planning \u2014 long-term objective management\n- Top-down flow: Strategy sets tactical goals, tactics set sensorimotor preferences\n- Bottom-up flow: Sensorimotor observations inform tactical beliefs, tactical outcomes inform strategy\n- Each level maintains its own generative model with A, B, C, D matrices\n- Timescale separation encoded via update ratios (Level 2 updates every 10 Level 0 steps)\n- Demonstrates deep temporal models from Friston et al. hierarchical Active Inference",
  "variables": [
    {
      "node_type": "Variable",
      "source_location": null,
      "metadata": {},
      "id": "bd566c51-2b21-455b-8380-310f0ebb3853",
      "name": "A0",
      "var_type": "action",
      "dimensions": [
        3,
        4
      ],
      "data_type": "float",
      "description": "Level 0 likelihood: P(fast_obs | fast_state)",
      "constraints": {}
    },
    {
      "node_type": "Variable",
      "source_location": null,
      "metadata": {},
      "id": "bc3a03c9-8e35-4dd8-8cab-8bc891db4798",
      "name": "B0",
      "var_type": "hidden_state",
      "dimensions": [
        4,
        4,
        3
      ],
      "data_type": "float",
      "description": "Level 0 transitions: P(fast_state' | fast_state, fast_action)",
      "constraints": {}
    },
    {
      "node_type": "Variable",
      "source_location": null,
      "metadata": {},
      "id": "a213fc3b-1cd4-4cc4-819c-293b99154c2a",
      "name": "C0",
      "var_type": "hidden_state",
      "dimensions": [
        3
      ],
      "data_type": "float",
      "description": "Level 0 preferences (modulated by Level 1)",
      "constraints": {}
    },
    {
      "node_type": "Variable",
      "source_location": null,
      "metadata": {},
      "id": "4a77dee8-768e-43df-9e28-f293576df317",
      "name": "D0",
      "var_type": "hidden_state",
      "dimensions": [
        4
      ],
      "data_type": "float",
      "description": "Level 0 prior over initial states",
      "constraints": {}
    },
    {
      "node_type": "Variable",
      "source_location": null,
      "metadata": {},
      "id": "04ed111f-8fd0-4bd7-b415-cd785beb7d6c",
      "name": "s0",
      "var_type": "hidden_state",
      "dimensions": [
        4,
        1
      ],
      "data_type": "float",
      "description": "Level 0 hidden state belief",
      "constraints": {}
    },
    {
      "node_type": "Variable",
      "source_location": null,
      "metadata": {},
      "id": "895aa5e2-5687-4b35-b65d-6104f309c844",
      "name": "o0",
      "var_type": "observation",
      "dimensions": [
        3,
        1
      ],
      "data_type": "integer",
      "description": "Level 0 observation",
      "constraints": {}
    },
    {
      "node_type": "Variable",
      "source_location": null,
      "metadata": {},
      "id": "2650dc11-8605-4521-8d63-5525220a9bed",
      "name": "pi0",
      "var_type": "policy",
      "dimensions": [
        3
      ],
      "data_type": "float",
      "description": "Level 0 policy",
      "constraints": {}
    },
    {
      "node_type": "Variable",
      "source_location": null,
      "metadata": {},
      "id": "f7433614-eed2-4e13-bf05-ede3ff4ead2c",
      "name": "u0",
      "var_type": "action",
      "dimensions": [
        1
      ],
      "data_type": "integer",
      "description": "Level 0 action",
      "constraints": {}
    },
    {
      "node_type": "Variable",
      "source_location": null,
      "metadata": {},
      "id": "2d8617f4-5aed-46db-aa80-ab0d3d84c49c",
      "name": "G0",
      "var_type": "hidden_state",
      "dimensions": [
        1
      ],
      "data_type": "float",
      "description": "Level 0 Expected Free Energy",
      "constraints": {}
    },
    {
      "node_type": "Variable",
      "source_location": null,
      "metadata": {},
      "id": "1b8a8587-f7d8-4a83-93a8-9000fd56e046",
      "name": "A1",
      "var_type": "action",
      "dimensions": [
        4,
        3
      ],
      "data_type": "float",
      "description": "Level 1 likelihood: P(tactic_obs | tactic_state)",
      "constraints": {}
    },
    {
      "node_type": "Variable",
      "source_location": null,
      "metadata": {},
      "id": "e1836aa8-85c3-4da3-97da-02034ba86c25",
      "name": "B1",
      "var_type": "hidden_state",
      "dimensions": [
        3,
        3,
        3
      ],
      "data_type": "float",
      "description": "Level 1 transitions",
      "constraints": {}
    },
    {
      "node_type": "Variable",
      "source_location": null,
      "metadata": {},
      "id": "3a903ba1-7794-464a-86e6-4be4b899c440",
      "name": "C1",
      "var_type": "hidden_state",
      "dimensions": [
        4
      ],
      "data_type": "float",
      "description": "Level 1 preferences (modulated by Level 2)",
      "constraints": {}
    },
    {
      "node_type": "Variable",
      "source_location": null,
      "metadata": {},
      "id": "427c0704-9cda-4973-be47-0c92a1b436ee",
      "name": "D1",
      "var_type": "hidden_state",
      "dimensions": [
        3
      ],
      "data_type": "float",
      "description": "Level 1 prior (modulated by Level 2 predictions)",
      "constraints": {}
    },
    {
      "node_type": "Variable",
      "source_location": null,
      "metadata": {},
      "id": "8fc088ac-578e-410a-b58c-222d19cf7676",
      "name": "s1",
      "var_type": "hidden_state",
      "dimensions": [
        3,
        1
      ],
      "data_type": "float",
      "description": "Level 1 hidden state belief",
      "constraints": {}
    },
    {
      "node_type": "Variable",
      "source_location": null,
      "metadata": {},
      "id": "01b4a5bc-9062-46df-ba1e-782fd942fea5",
      "name": "o1",
      "var_type": "observation",
      "dimensions": [
        4,
        1
      ],
      "data_type": "float",
      "description": "Level 1 observation (= summary of Level 0 state trajectory)",
      "constraints": {}
    },
    {
      "node_type": "Variable",
      "source_location": null,
      "metadata": {},
      "id": "d06e6ae1-c682-4746-a5fc-bc8da94443da",
      "name": "pi1",
      "var_type": "policy",
      "dimensions": [
        3
      ],
      "data_type": "float",
      "description": "Level 1 policy",
      "constraints": {}
    },
    {
      "node_type": "Variable",
      "source_location": null,
      "metadata": {},
      "id": "ce48c866-1b19-49d3-a3a2-54bf6bb5820b",
      "name": "u1",
      "var_type": "action",
      "dimensions": [
        1
      ],
      "data_type": "integer",
      "description": "Level 1 action",
      "constraints": {}
    },
    {
      "node_type": "Variable",
      "source_location": null,
      "metadata": {},
      "id": "7cf7ed66-8c35-4340-984e-19058e06c358",
      "name": "G1",
      "var_type": "hidden_state",
      "dimensions": [
        1
      ],
      "data_type": "float",
      "description": "Level 1 Expected Free Energy",
      "constraints": {}
    },
    {
      "node_type": "Variable",
      "source_location": null,
      "metadata": {},
      "id": "ad5b0b8f-0b6f-4641-978e-f3886b5d478e",
      "name": "A2",
      "var_type": "action",
      "dimensions": [
        3,
        2
      ],
      "data_type": "float",
      "description": "Level 2 likelihood: P(strategy_obs | strategy_state)",
      "constraints": {}
    },
    {
      "node_type": "Variable",
      "source_location": null,
      "metadata": {},
      "id": "141a31e7-0ea6-480e-94e6-d2036462104d",
      "name": "B2",
      "var_type": "hidden_state",
      "dimensions": [
        2,
        2,
        2
      ],
      "data_type": "float",
      "description": "Level 2 transitions",
      "constraints": {}
    },
    {
      "node_type": "Variable",
      "source_location": null,
      "metadata": {},
      "id": "a52c4897-1478-4fdb-9e6b-233c93d59656",
      "name": "C2",
      "var_type": "hidden_state",
      "dimensions": [
        3
      ],
      "data_type": "float",
      "description": "Level 2 preferences (fixed strategic goals)",
      "constraints": {}
    },
    {
      "node_type": "Variable",
      "source_location": null,
      "metadata": {},
      "id": "95031015-a923-4338-bbfa-f4b18e28a292",
      "name": "D2",
      "var_type": "hidden_state",
      "dimensions": [
        2
      ],
      "data_type": "float",
      "description": "Level 2 prior over strategies",
      "constraints": {}
    },
    {
      "node_type": "Variable",
      "source_location": null,
      "metadata": {},
      "id": "0dc13327-8342-4c41-91eb-ba997aa898fe",
      "name": "s2",
      "var_type": "hidden_state",
      "dimensions": [
        2,
        1
      ],
      "data_type": "float",
      "description": "Level 2 hidden state belief",
      "constraints": {}
    },
    {
      "node_type": "Variable",
      "source_location": null,
      "metadata": {},
      "id": "d005de40-d2f9-4ce6-81d1-4250fe9c1092",
      "name": "o2",
      "var_type": "observation",
      "dimensions": [
        3,
        1
      ],
      "data_type": "float",
      "description": "Level 2 observation (= summary of Level 1 outcomes)",
      "constraints": {}
    },
    {
      "node_type": "Variable",
      "source_location": null,
      "metadata": {},
      "id": "5847bf71-1a04-48e4-8ddf-0aa67ef2572e",
      "name": "pi2",
      "var_type": "policy",
      "dimensions": [
        2
      ],
      "data_type": "float",
      "description": "Level 2 policy",
      "constraints": {}
    },
    {
      "node_type": "Variable",
      "source_location": null,
      "metadata": {},
      "id": "2aa21a0b-5dc4-4723-a599-edb8297e3b30",
      "name": "u2",
      "var_type": "action",
      "dimensions": [
        1
      ],
      "data_type": "integer",
      "description": "Level 2 action",
      "constraints": {}
    },
    {
      "node_type": "Variable",
      "source_location": null,
      "metadata": {},
      "id": "23d042aa-8a2e-4bff-9afb-4a2188f6b183",
      "name": "G2",
      "var_type": "hidden_state",
      "dimensions": [
        1
      ],
      "data_type": "float",
      "description": "Level 2 Expected Free Energy",
      "constraints": {}
    },
    {
      "node_type": "Variable",
      "source_location": null,
      "metadata": {},
      "id": "b964c758-1af6-4074-817e-0cb99cd0de3c",
      "name": "tau0",
      "var_type": "hidden_state",
      "dimensions": [
        1
      ],
      "data_type": "float",
      "description": "Level 0 time constant (0.1s)",
      "constraints": {}
    },
    {
      "node_type": "Variable",
      "source_location": null,
      "metadata": {},
      "id": "5eca551d-380a-48c6-b2dd-c3a30cefce4d",
      "name": "tau1",
      "var_type": "hidden_state",
      "dimensions": [
        1
      ],
      "data_type": "float",
      "description": "Level 1 time constant (1.0s)",
      "constraints": {}
    },
    {
      "node_type": "Variable",
      "source_location": null,
      "metadata": {},
      "id": "d491a52c-c934-4b92-adba-7662baf79221",
      "name": "tau2",
      "var_type": "hidden_state",
      "dimensions": [
        1
      ],
      "data_type": "float",
      "description": "Level 2 time constant (10.0s)",
      "constraints": {}
    },
    {
      "node_type": "Variable",
      "source_location": null,
      "metadata": {},
      "id": "4e8f29b5-df20-4f4a-b5ea-bf7bec3782d9",
      "name": "t",
      "var_type": "hidden_state",
      "dimensions": [
        1
      ],
      "data_type": "integer",
      "description": "Global discrete time counter",
      "constraints": {}
    }
  ],
  "connections": [
    {
      "node_type": "Connection",
      "source_location": null,
      "metadata": {},
      "id": "01d8c907-6c43-43f5-aef3-dca6ffec9f70",
      "source_variables": [
        "D0"
      ],
      "target_variables": [
        "s0"
      ],
      "connection_type": "directed",
      "weight": null,
      "description": null
    },
    {
      "node_type": "Connection",
      "source_location": null,
      "metadata": {},
      "id": "d66c5f5e-25b7-4cf5-8384-e9260f48e2ed",
      "source_variables": [
        "s0"
      ],
      "target_variables": [
        "A0"
      ],
      "connection_type": "undirected",
      "weight": null,
      "description": null
    },
    {
      "node_type": "Connection",
      "source_location": null,
      "metadata": {},
      "id": "6b5aaee8-1724-4dd7-814f-9326964a1f68",
      "source_variables": [
        "A0"
      ],
      "target_variables": [
        "o0"
      ],
      "connection_type": "undirected",
      "weight": null,
      "description": null
    },
    {
      "node_type": "Connection",
      "source_location": null,
      "metadata": {},
      "id": "4cfeefed-e568-4edd-abda-0e7d7d2d2a2e",
      "source_variables": [
        "C0"
      ],
      "target_variables": [
        "G0"
      ],
      "connection_type": "directed",
      "weight": null,
      "description": null
    },
    {
      "node_type": "Connection",
      "source_location": null,
      "metadata": {},
      "id": "bdcbd0c1-1613-4722-a0a3-ff49c5fd7552",
      "source_variables": [
        "G0"
      ],
      "target_variables": [
        "pi0"
      ],
      "connection_type": "directed",
      "weight": null,
      "description": null
    },
    {
      "node_type": "Connection",
      "source_location": null,
      "metadata": {},
      "id": "b0be1b30-0ea0-41ab-b5f2-1496cd5e1198",
      "source_variables": [
        "pi0"
      ],
      "target_variables": [
        "u0"
      ],
      "connection_type": "directed",
      "weight": null,
      "description": null
    },
    {
      "node_type": "Connection",
      "source_location": null,
      "metadata": {},
      "id": "e90250ed-28ac-4e39-ad47-30375773d1c4",
      "source_variables": [
        "B0"
      ],
      "target_variables": [
        "u0"
      ],
      "connection_type": "directed",
      "weight": null,
      "description": null
    },
    {
      "node_type": "Connection",
      "source_location": null,
      "metadata": {},
      "id": "689e9a59-13e6-4a7f-9eca-345a71363d9d",
      "source_variables": [
        "D1"
      ],
      "target_variables": [
        "s1"
      ],
      "connection_type": "directed",
      "weight": null,
      "description": null
    },
    {
      "node_type": "Connection",
      "source_location": null,
      "metadata": {},
      "id": "ce7c57c8-8c63-45ef-9d60-b66bb8fa74d9",
      "source_variables": [
        "s1"
      ],
      "target_variables": [
        "A1"
      ],
      "connection_type": "undirected",
      "weight": null,
      "description": null
    },
    {
      "node_type": "Connection",
      "source_location": null,
      "metadata": {},
      "id": "d1f8aa6c-3e6e-44d1-8d9e-add49426700d",
      "source_variables": [
        "A1"
      ],
      "target_variables": [
        "o1"
      ],
      "connection_type": "undirected",
      "weight": null,
      "description": null
    },
    {
      "node_type": "Connection",
      "source_location": null,
      "metadata": {},
      "id": "7d95dff5-1703-46ba-abf2-cb8fcf9bb262",
      "source_variables": [
        "C1"
      ],
      "target_variables": [
        "G1"
      ],
      "connection_type": "directed",
      "weight": null,
      "description": null
    },
    {
      "node_type": "Connection",
      "source_location": null,
      "metadata": {},
      "id": "b4682ccf-c007-4d7b-bf6f-96ffdde5b812",
      "source_variables": [
        "G1"
      ],
      "target_variables": [
        "pi1"
      ],
      "connection_type": "directed",
      "weight": null,
      "description": null
    },
    {
      "node_type": "Connection",
      "source_location": null,
      "metadata": {},
      "id": "a01ce3fb-e93d-499d-bdca-7bcd957900e8",
      "source_variables": [
        "pi1"
      ],
      "target_variables": [
        "u1"
      ],
      "connection_type": "directed",
      "weight": null,
      "description": null
    },
    {
      "node_type": "Connection",
      "source_location": null,
      "metadata": {},
      "id": "bf58c640-d877-434f-8447-06a192f8b4e3",
      "source_variables": [
        "B1"
      ],
      "target_variables": [
        "u1"
      ],
      "connection_type": "directed",
      "weight": null,
      "description": null
    },
    {
      "node_type": "Connection",
      "source_location": null,
      "metadata": {},
      "id": "c3b6ed51-9434-4728-adb0-cb1a610ecb7c",
      "source_variables": [
        "D2"
      ],
      "target_variables": [
        "s2"
      ],
      "connection_type": "directed",
      "weight": null,
      "description": null
    },
    {
      "node_type": "Connection",
      "source_location": null,
      "metadata": {},
      "id": "8d5f3a79-d5f7-427b-ac05-bcbc705d0fb7",
      "source_variables": [
        "s2"
      ],
      "target_variables": [
        "A2"
      ],
      "connection_type": "undirected",
      "weight": null,
      "description": null
    },
    {
      "node_type": "Connection",
      "source_location": null,
      "metadata": {},
      "id": "f2180775-9f57-4b8e-9048-e3b5c4837921",
      "source_variables": [
        "A2"
      ],
      "target_variables": [
        "o2"
      ],
      "connection_type": "undirected",
      "weight": null,
      "description": null
    },
    {
      "node_type": "Connection",
      "source_location": null,
      "metadata": {},
      "id": "cc8fdd97-7064-4b14-9819-55fb0125aefd",
      "source_variables": [
        "C2"
      ],
      "target_variables": [
        "G2"
      ],
      "connection_type": "directed",
      "weight": null,
      "description": null
    },
    {
      "node_type": "Connection",
      "source_location": null,
      "metadata": {},
      "id": "7ba3ce72-5cd7-43ec-845d-c61e76259a34",
      "source_variables": [
        "G2"
      ],
      "target_variables": [
        "pi2"
      ],
      "connection_type": "directed",
      "weight": null,
      "description": null
    },
    {
      "node_type": "Connection",
      "source_location": null,
      "metadata": {},
      "id": "5a3331d4-1ec2-42d1-8036-a778acf6edaa",
      "source_variables": [
        "pi2"
      ],
      "target_variables": [
        "u2"
      ],
      "connection_type": "directed",
      "weight": null,
      "description": null
    },
    {
      "node_type": "Connection",
      "source_location": null,
      "metadata": {},
      "id": "4be8e47d-1d7a-4471-9767-ef40b4e366aa",
      "source_variables": [
        "B2"
      ],
      "target_variables": [
        "u2"
      ],
      "connection_type": "directed",
      "weight": null,
      "description": null
    },
    {
      "node_type": "Connection",
      "source_location": null,
      "metadata": {},
      "id": "4abf70f6-7fb6-4d00-9d3e-8ea5216f1282",
      "source_variables": [
        "s2"
      ],
      "target_variables": [
        "C1"
      ],
      "connection_type": "directed",
      "weight": null,
      "description": null
    },
    {
      "node_type": "Connection",
      "source_location": null,
      "metadata": {},
      "id": "65d5d94b-c595-451b-a169-5f1f33a722bf",
      "source_variables": [
        "s1"
      ],
      "target_variables": [
        "C0"
      ],
      "connection_type": "directed",
      "weight": null,
      "description": null
    },
    {
      "node_type": "Connection",
      "source_location": null,
      "metadata": {},
      "id": "9f5e79e2-b946-4a45-a2c7-359acc703bf9",
      "source_variables": [
        "s2"
      ],
      "target_variables": [
        "D1"
      ],
      "connection_type": "directed",
      "weight": null,
      "description": null
    },
    {
      "node_type": "Connection",
      "source_location": null,
      "metadata": {},
      "id": "2bb6e249-887f-48a8-b38a-2818832365be",
      "source_variables": [
        "s0"
      ],
      "target_variables": [
        "o1"
      ],
      "connection_type": "directed",
      "weight": null,
      "description": null
    },
    {
      "node_type": "Connection",
      "source_location": null,
      "metadata": {},
      "id": "87e08967-1d06-4409-866a-b1d882ef9ff2",
      "source_variables": [
        "s1"
      ],
      "target_variables": [
        "o2"
      ],
      "connection_type": "directed",
      "weight": null,
      "description": null
    }
  ],
  "parameters": [
    {
      "node_type": "Parameter",
      "source_location": null,
      "metadata": {},
      "id": "90ca26b4-4df2-4502-a36f-0c8b09b3eada",
      "name": "A0",
      "value": [
        [
          0.85,
          0.05,
          0.05,
          0.05
        ],
        [
          0.05,
          0.85,
          0.05,
          0.05
        ],
        [
          0.05,
          0.05,
          0.85,
          0.05
        ]
      ],
      "type_hint": null,
      "description": null
    },
    {
      "node_type": "Parameter",
      "source_location": null,
      "metadata": {},
      "id": "8ae243ad-5084-4544-a876-c222736422f5",
      "name": "C0",
      "value": [
        [
          0.0,
          -1.0,
          1.0
        ]
      ],
      "type_hint": null,
      "description": null
    },
    {
      "node_type": "Parameter",
      "source_location": null,
      "metadata": {},
      "id": "faebace4-9224-43b0-b5c3-b178bad9d7a0",
      "name": "D0",
      "value": [
        [
          0.25,
          0.25,
          0.25,
          0.25
        ]
      ],
      "type_hint": null,
      "description": null
    },
    {
      "node_type": "Parameter",
      "source_location": null,
      "metadata": {},
      "id": "d2958b25-5b39-4213-a8b5-83b02466f8f1",
      "name": "A1",
      "value": [
        [
          0.8,
          0.1,
          0.1
        ],
        [
          0.1,
          0.8,
          0.1
        ],
        [
          0.1,
          0.1,
          0.8
        ],
        [
          0.1,
          0.1,
          0.1
        ]
      ],
      "type_hint": null,
      "description": null
    },
    {
      "node_type": "Parameter",
      "source_location": null,
      "metadata": {},
      "id": "a6435451-2397-4bf3-90ef-e1bb44c00c03",
      "name": "C1",
      "value": [
        [
          -0.5,
          1.0,
          1.5,
          -1.0
        ]
      ],
      "type_hint": null,
      "description": null
    },
    {
      "node_type": "Parameter",
      "source_location": null,
      "metadata": {},
      "id": "76deb2fb-e150-4ec6-8a2c-9e965e8c2015",
      "name": "D1",
      "value": [
        [
          0.33,
          0.33,
          0.34
        ]
      ],
      "type_hint": null,
      "description": null
    },
    {
      "node_type": "Parameter",
      "source_location": null,
      "metadata": {},
      "id": "5369dff0-3725-4a38-ba14-c38af8e31f95",
      "name": "A2",
      "value": [
        [
          0.9,
          0.1
        ],
        [
          0.1,
          0.9
        ],
        [
          0.1,
          0.1
        ]
      ],
      "type_hint": null,
      "description": null
    },
    {
      "node_type": "Parameter",
      "source_location": null,
      "metadata": {},
      "id": "e9063a87-c873-42ca-b28c-b271037f0bc8",
      "name": "C2",
      "value": [
        [
          -1.0,
          2.0,
          0.5
        ]
      ],
      "type_hint": null,
      "description": null
    },
    {
      "node_type": "Parameter",
      "source_location": null,
      "metadata": {},
      "id": "593105af-329e-4a17-a4c4-4a43cc1053a5",
      "name": "D2",
      "value": [
        [
          0.5,
          0.5
        ]
      ],
      "type_hint": null,
      "description": null
    },
    {
      "node_type": "Parameter",
      "source_location": null,
      "metadata": {},
      "id": "9bf7410e-d752-4a51-9504-9e087b89f873",
      "name": "tau0",
      "value": [
        [
          0.1
        ]
      ],
      "type_hint": null,
      "description": null
    },
    {
      "node_type": "Parameter",
      "source_location": null,
      "metadata": {},
      "id": "d7acc056-aa44-4e14-8b8c-a5f5c30fbd0a",
      "name": "tau1",
      "value": [
        [
          1.0
        ]
      ],
      "type_hint": null,
      "description": null
    },
    {
      "node_type": "Parameter",
      "source_location": null,
      "metadata": {},
      "id": "28939a5e-2f42-4659-9d86-43c6b22862e6",
      "name": "tau2",
      "value": [
        [
          10.0
        ]
      ],
      "type_hint": null,
      "description": null
    }
  ],
  "equations": [],
  "time_specification": {
    "node_type": "TimeSpecification",
    "source_location": null,
    "metadata": {},
    "id": "7cd2cfdb-550e-40cc-aed0-e1cc9df9aae0",
    "time_type": "Dynamic",
    "discretization": null,
    "horizon": 100,
    "step_size": null
  },
  "ontology_mappings": [
    {
      "node_type": "OntologyMapping",
      "source_location": null,
      "metadata": {},
      "id": "1cd94f1a-70ce-4d2f-9c66-b47c2db330c2",
      "variable_name": "A0",
      "ontology_term": "FastLikelihoodMatrix",
      "description": null
    },
    {
      "node_type": "OntologyMapping",
      "source_location": null,
      "metadata": {},
      "id": "b9cba9fd-8d17-43ed-9a4b-f0286b56bad9",
      "variable_name": "B0",
      "ontology_term": "FastTransitionMatrix",
      "description": null
    },
    {
      "node_type": "OntologyMapping",
      "source_location": null,
      "metadata": {},
      "id": "3571019a-989a-4770-91df-143edc86d434",
      "variable_name": "C0",
      "ontology_term": "FastPreferenceVector",
      "description": null
    },
    {
      "node_type": "OntologyMapping",
      "source_location": null,
      "metadata": {},
      "id": "87fe496c-62ac-44a3-9cc7-49e056eac65a",
      "variable_name": "D0",
      "ontology_term": "FastPrior",
      "description": null
    },
    {
      "node_type": "OntologyMapping",
      "source_location": null,
      "metadata": {},
      "id": "a8a5508d-2e84-40e0-b0a8-779236ae74fe",
      "variable_name": "s0",
      "ontology_term": "FastHiddenState",
      "description": null
    },
    {
      "node_type": "OntologyMapping",
      "source_location": null,
      "metadata": {},
      "id": "2639b2e0-7b74-40bc-80ca-f6d1f7e83ae8",
      "variable_name": "o0",
      "ontology_term": "FastObservation",
      "description": null
    },
    {
      "node_type": "OntologyMapping",
      "source_location": null,
      "metadata": {},
      "id": "e0089a25-ebf1-4bd8-a246-a328ac4dd821",
      "variable_name": "pi0",
      "ontology_term": "FastPolicyVector",
      "description": null
    },
    {
      "node_type": "OntologyMapping",
      "source_location": null,
      "metadata": {},
      "id": "2c0cf589-3381-4800-9b8c-594141471b40",
      "variable_name": "u0",
      "ontology_term": "FastAction",
      "description": null
    },
    {
      "node_type": "OntologyMapping",
      "source_location": null,
      "metadata": {},
      "id": "7bf3821b-8ad4-41b0-93b7-4266441a139a",
      "variable_name": "G0",
      "ontology_term": "FastExpectedFreeEnergy",
      "description": null
    },
    {
      "node_type": "OntologyMapping",
      "source_location": null,
      "metadata": {},
      "id": "c83ebe53-89be-4341-a29f-3873f86cb4ab",
      "variable_name": "A1",
      "ontology_term": "TacticalLikelihoodMatrix",
      "description": null
    },
    {
      "node_type": "OntologyMapping",
      "source_location": null,
      "metadata": {},
      "id": "e5a05c0f-d143-4220-bdc7-cb0c5cf6a616",
      "variable_name": "B1",
      "ontology_term": "TacticalTransitionMatrix",
      "description": null
    },
    {
      "node_type": "OntologyMapping",
      "source_location": null,
      "metadata": {},
      "id": "68c285f9-b3e7-4fde-a2e0-bcf7d100be68",
      "variable_name": "C1",
      "ontology_term": "TacticalPreferenceVector",
      "description": null
    },
    {
      "node_type": "OntologyMapping",
      "source_location": null,
      "metadata": {},
      "id": "cc18cea2-f257-45e8-b011-21152936b911",
      "variable_name": "D1",
      "ontology_term": "TacticalPrior",
      "description": null
    },
    {
      "node_type": "OntologyMapping",
      "source_location": null,
      "metadata": {},
      "id": "e6fbe47e-6083-421d-86ad-67f5d9e54763",
      "variable_name": "s1",
      "ontology_term": "TacticalHiddenState",
      "description": null
    },
    {
      "node_type": "OntologyMapping",
      "source_location": null,
      "metadata": {},
      "id": "7e516b3c-0b6b-4b6f-a1b4-405525adf443",
      "variable_name": "o1",
      "ontology_term": "TacticalObservation",
      "description": null
    },
    {
      "node_type": "OntologyMapping",
      "source_location": null,
      "metadata": {},
      "id": "39f0cb43-3120-4119-8287-81cc54a2e925",
      "variable_name": "pi1",
      "ontology_term": "TacticalPolicyVector",
      "description": null
    },
    {
      "node_type": "OntologyMapping",
      "source_location": null,
      "metadata": {},
      "id": "1769f535-ef93-40f5-a80c-93487bbcb26d",
      "variable_name": "u1",
      "ontology_term": "TacticalAction",
      "description": null
    },
    {
      "node_type": "OntologyMapping",
      "source_location": null,
      "metadata": {},
      "id": "e99aaef4-e806-490f-bdc7-2586041782d0",
      "variable_name": "G1",
      "ontology_term": "TacticalExpectedFreeEnergy",
      "description": null
    },
    {
      "node_type": "OntologyMapping",
      "source_location": null,
      "metadata": {},
      "id": "1062ca77-0957-45df-80b9-56802f8a97cc",
      "variable_name": "A2",
      "ontology_term": "StrategicLikelihoodMatrix",
      "description": null
    },
    {
      "node_type": "OntologyMapping",
      "source_location": null,
      "metadata": {},
      "id": "f125bf47-0bbc-401b-8d28-ebd4b00827cc",
      "variable_name": "B2",
      "ontology_term": "StrategicTransitionMatrix",
      "description": null
    },
    {
      "node_type": "OntologyMapping",
      "source_location": null,
      "metadata": {},
      "id": "87f52fac-d2fb-4242-bb1c-18cefa4784e5",
      "variable_name": "C2",
      "ontology_term": "StrategicPreferenceVector",
      "description": null
    },
    {
      "node_type": "OntologyMapping",
      "source_location": null,
      "metadata": {},
      "id": "51ad3659-e033-4572-9ae4-6877e9b57c8a",
      "variable_name": "D2",
      "ontology_term": "StrategicPrior",
      "description": null
    },
    {
      "node_type": "OntologyMapping",
      "source_location": null,
      "metadata": {},
      "id": "127e6b0f-2f9d-4503-b987-aeccdc58878a",
      "variable_name": "s2",
      "ontology_term": "StrategicHiddenState",
      "description": null
    },
    {
      "node_type": "OntologyMapping",
      "source_location": null,
      "metadata": {},
      "id": "3a9c3896-08a2-4992-90ac-9a57d2a42705",
      "variable_name": "o2",
      "ontology_term": "StrategicObservation",
      "description": null
    },
    {
      "node_type": "OntologyMapping",
      "source_location": null,
      "metadata": {},
      "id": "82f3f302-685b-43f3-8c22-35403b674b6b",
      "variable_name": "pi2",
      "ontology_term": "StrategicPolicyVector",
      "description": null
    },
    {
      "node_type": "OntologyMapping",
      "source_location": null,
      "metadata": {},
      "id": "59e30b7e-2137-449b-8526-e27731598c97",
      "variable_name": "u2",
      "ontology_term": "StrategicAction",
      "description": null
    },
    {
      "node_type": "OntologyMapping",
      "source_location": null,
      "metadata": {},
      "id": "eb6a8bad-d183-4538-899f-517ed21e9e33",
      "variable_name": "G2",
      "ontology_term": "StrategicExpectedFreeEnergy",
      "description": null
    },
    {
      "node_type": "OntologyMapping",
      "source_location": null,
      "metadata": {},
      "id": "6ef8e9c5-75e0-4b0d-8f4b-adc5e6fe8c87",
      "variable_name": "tau0",
      "ontology_term": "FastTimeConstant",
      "description": null
    },
    {
      "node_type": "OntologyMapping",
      "source_location": null,
      "metadata": {},
      "id": "da8a80f5-ab8d-48dd-92da-f19e502716a4",
      "variable_name": "tau1",
      "ontology_term": "TacticalTimeConstant",
      "description": null
    },
    {
      "node_type": "OntologyMapping",
      "source_location": null,
      "metadata": {},
      "id": "7c95ed13-b053-485a-b49d-7cd3e2391dab",
      "variable_name": "tau2",
      "ontology_term": "StrategicTimeConstant",
      "description": null
    },
    {
      "node_type": "OntologyMapping",
      "source_location": null,
      "metadata": {},
      "id": "765157bd-9a78-4b90-a58f-5558a437ad45",
      "variable_name": "t",
      "ontology_term": "Time",
      "description": null
    }
  ],
  "source_format": null,
  "created_at": "2026-03-13T14:15:03.066303",
  "modified_at": "2026-03-13T14:15:03.066304",
  "checksum": null,
  "extensions": {
    "gnn_section": "ActInfPOMDP_Hierarchical",
    "footer": "Three-Level Temporal Hierarchy Agent v1 - GNN Representation.\nFast (100ms sensorimotor), Medium (1s tactical), Slow (10s strategic).\nTop-down: strategy \u2192 tactics \u2192 sensorimotor preferences.\nBottom-up: sensory evidence \u2192 tactical summaries \u2192 strategic outcomes.",
    "signature": "Cryptographic signature goes here"
  },
  "raw_sections": {
    "GNNSection": "ActInfPOMDP_Hierarchical",
    "GNNVersionAndFlags": "GNN v1",
    "ModelName": "Three-Level Temporal Hierarchy Agent",
    "ModelAnnotation": "A three-level hierarchical Active Inference agent with distinct temporal scales:\n\n- Level 0 (fast, 100ms): Sensorimotor control \u2014 immediate reflexive responses\n- Level 1 (medium, 1s): Tactical planning \u2014 goal-directed behavior sequences\n- Level 2 (slow, 10s): Strategic planning \u2014 long-term objective management\n- Top-down flow: Strategy sets tactical goals, tactics set sensorimotor preferences\n- Bottom-up flow: Sensorimotor observations inform tactical beliefs, tactical outcomes inform strategy\n- Each level maintains its own generative model with A, B, C, D matrices\n- Timescale separation encoded via update ratios (Level 2 updates every 10 Level 0 steps)\n- Demonstrates deep temporal models from Friston et al. hierarchical Active Inference",
    "StateSpaceBlock": "# Level 0: Fast sensorimotor (4 states, 3 obs, 3 actions)\n\nA0[3,4,type=float]         # Level 0 likelihood: P(fast_obs | fast_state)\nB0[4,4,3,type=float]       # Level 0 transitions: P(fast_state' | fast_state, fast_action)\nC0[3,type=float]           # Level 0 preferences (modulated by Level 1)\nD0[4,type=float]           # Level 0 prior over initial states\ns0[4,1,type=float]         # Level 0 hidden state belief\no0[3,1,type=int]           # Level 0 observation\npi0[3,type=float]          # Level 0 policy\nu0[1,type=int]             # Level 0 action\nG0[pi0,type=float]         # Level 0 Expected Free Energy\n\n# Level 1: Medium tactical (3 states, 4 obs, 3 actions)\n\nA1[4,3,type=float]         # Level 1 likelihood: P(tactic_obs | tactic_state)\nB1[3,3,3,type=float]       # Level 1 transitions\nC1[4,type=float]           # Level 1 preferences (modulated by Level 2)\nD1[3,type=float]           # Level 1 prior (modulated by Level 2 predictions)\ns1[3,1,type=float]         # Level 1 hidden state belief\no1[4,1,type=float]         # Level 1 observation (= summary of Level 0 state trajectory)\npi1[3,type=float]          # Level 1 policy\nu1[1,type=int]             # Level 1 action\nG1[pi1,type=float]         # Level 1 Expected Free Energy\n\n# Level 2: Slow strategic (2 states, 3 obs, 2 actions)\n\nA2[3,2,type=float]         # Level 2 likelihood: P(strategy_obs | strategy_state)\nB2[2,2,2,type=float]       # Level 2 transitions\nC2[3,type=float]           # Level 2 preferences (fixed strategic goals)\nD2[2,type=float]           # Level 2 prior over strategies\ns2[2,1,type=float]         # Level 2 hidden state belief\no2[3,1,type=float]         # Level 2 observation (= summary of Level 1 outcomes)\npi2[2,type=float]          # Level 2 policy\nu2[1,type=int]             # Level 2 action\nG2[pi2,type=float]         # Level 2 Expected Free Energy\n\n# Timescale parameters\n\ntau0[1,type=float]         # Level 0 time constant (0.1s)\ntau1[1,type=float]         # Level 1 time constant (1.0s)\ntau2[1,type=float]         # Level 2 time constant (10.0s)\n\n# Time\n\nt[1,type=int]              # Global discrete time counter",
    "Connections": "# Level 0 (fast) internal loop\n\nD0>s0\ns0-A0\nA0-o0\nC0>G0\nG0>pi0\npi0>u0\nB0>u0\n\n# Level 1 (medium) internal loop\n\nD1>s1\ns1-A1\nA1-o1\nC1>G1\nG1>pi1\npi1>u1\nB1>u1\n\n# Level 2 (slow) internal loop\n\nD2>s2\ns2-A2\nA2-o2\nC2>G2\nG2>pi2\npi2>u2\nB2>u2\n\n# Top-down causal flow (context modulates subordinate levels)\n\ns2>C1\ns1>C0\ns2>D1\n\n# Bottom-up evidential flow (observations inform superior levels)\n\ns0>o1\ns1>o2",
    "InitialParameterization": "# Level 0: Sensorimotor (fast, reflexive)\n\nA0={\n  (0.85, 0.05, 0.05, 0.05),\n  (0.05, 0.85, 0.05, 0.05),\n  (0.05, 0.05, 0.85, 0.05)\n}\n\nC0={(0.0, -1.0, 1.0)}\nD0={(0.25, 0.25, 0.25, 0.25)}\n\n# Level 1: Tactical\n\nA1={\n  (0.8, 0.1, 0.1),\n  (0.1, 0.8, 0.1),\n  (0.1, 0.1, 0.8),\n  (0.1, 0.1, 0.1)\n}\n\nC1={(-0.5, 1.0, 1.5, -1.0)}\nD1={(0.33, 0.33, 0.34)}\n\n# Level 2: Strategic\n\nA2={\n  (0.9, 0.1),\n  (0.1, 0.9),\n  (0.1, 0.1)\n}\n\nC2={(-1.0, 2.0, 0.5)}\nD2={(0.5, 0.5)}\n\n# Timescale constants\n\ntau0={(0.1)}\ntau1={(1.0)}\ntau2={(10.0)}",
    "Equations": "# Each level runs standard Active Inference\n\n# Perception: Q(s) = softmax(ln D + ln A^T o)\n\n# Policy: pi = softmax(-G + ln E)\n\n# EFE: G(pi) = epistemic + instrumental\n\n# Cross-level interactions\n\n# Top-down: C_lower = f(s_higher) \u2014 higher beliefs set lower preferences\n\n# Bottom-up: o_higher = h(s_lower) \u2014 lower state trajectory summarized as higher observation\n\n# Timescale separation: Level k updates every (tau_k / tau_0) Level 0 steps",
    "Time": "Time=t\nDynamic\nDiscrete\nModelTimeHorizon=100",
    "ActInfOntologyAnnotation": "A0=FastLikelihoodMatrix\nB0=FastTransitionMatrix\nC0=FastPreferenceVector\nD0=FastPrior\ns0=FastHiddenState\no0=FastObservation\npi0=FastPolicyVector\nu0=FastAction\nG0=FastExpectedFreeEnergy\nA1=TacticalLikelihoodMatrix\nB1=TacticalTransitionMatrix\nC1=TacticalPreferenceVector\nD1=TacticalPrior\ns1=TacticalHiddenState\no1=TacticalObservation\npi1=TacticalPolicyVector\nu1=TacticalAction\nG1=TacticalExpectedFreeEnergy\nA2=StrategicLikelihoodMatrix\nB2=StrategicTransitionMatrix\nC2=StrategicPreferenceVector\nD2=StrategicPrior\ns2=StrategicHiddenState\no2=StrategicObservation\npi2=StrategicPolicyVector\nu2=StrategicAction\nG2=StrategicExpectedFreeEnergy\ntau0=FastTimeConstant\ntau1=TacticalTimeConstant\ntau2=StrategicTimeConstant\nt=Time",
    "ModelParameters": "num_levels: 3\nnum_states_l0: 4\nnum_obs_l0: 3\nnum_actions_l0: 3\nnum_states_l1: 3\nnum_obs_l1: 4\nnum_actions_l1: 3\nnum_states_l2: 2\nnum_obs_l2: 3\nnum_actions_l2: 2\ntimescale_ratio_1_0: 10\ntimescale_ratio_2_1: 10\nnum_timesteps: 100",
    "Footer": "Three-Level Temporal Hierarchy Agent v1 - GNN Representation.\nFast (100ms sensorimotor), Medium (1s tactical), Slow (10s strategic).\nTop-down: strategy \u2192 tactics \u2192 sensorimotor preferences.\nBottom-up: sensory evidence \u2192 tactical summaries \u2192 strategic outcomes.",
    "Signature": "Cryptographic signature goes here"
  }
}