[
  {
    "name": "get_pipeline_config_info",
    "description": "Get detailed pipeline configuration information and settings.",
    "module": "",
    "category": "",
    "version": "1.0.0"
  },
  {
    "name": "get_pipeline_status",
    "description": "Get current pipeline execution status, recent logs, and execution statistics.",
    "module": "",
    "category": "",
    "version": "1.0.0"
  },
  {
    "name": "get_pipeline_steps",
    "description": "Get information about all available pipeline steps, their metadata, and dependencies.",
    "module": "",
    "category": "",
    "version": "1.0.0"
  },
  {
    "name": "sympy_analyze_stability",
    "description": "Analyze system stability using eigenvalue analysis",
    "module": "",
    "category": "",
    "version": "1.0.0"
  },
  {
    "name": "sympy_cleanup",
    "description": "Clean up SymPy MCP integration and reset state",
    "module": "",
    "category": "",
    "version": "1.0.0"
  },
  {
    "name": "sympy_get_latex",
    "description": "Convert a mathematical expression to LaTeX format",
    "module": "",
    "category": "",
    "version": "1.0.0"
  },
  {
    "name": "sympy_initialize",
    "description": "Initialize SymPy MCP integration",
    "module": "",
    "category": "",
    "version": "1.0.0"
  },
  {
    "name": "sympy_simplify_expression",
    "description": "Simplify a mathematical expression to canonical form",
    "module": "",
    "category": "",
    "version": "1.0.0"
  },
  {
    "name": "sympy_solve_equation",
    "description": "Solve an equation algebraically for a specified variable",
    "module": "",
    "category": "",
    "version": "1.0.0"
  },
  {
    "name": "sympy_validate_equation",
    "description": "Validate a mathematical equation using SymPy symbolic processing",
    "module": "",
    "category": "",
    "version": "1.0.0"
  },
  {
    "name": "sympy_validate_matrix",
    "description": "Validate matrix properties including stochasticity constraints",
    "module": "",
    "category": "",
    "version": "1.0.0"
  },
  {
    "name": "validate_pipeline_dependencies",
    "description": "Validate pipeline step dependencies and identify missing or circular dependencies.",
    "module": "",
    "category": "",
    "version": "1.0.0"
  }
]